spectronote/__init__.py
spectronote/__main__.py
spectronote/scene.py
spectronote/resources/images/logo.png
spectronote/resources/images/logo.svg
spectronote/resources/shaders/spectronote.frag
spectronote-0.9.1.dist-info/METADATA
spectronote-0.9.1.dist-info/WHEEL
spectronote-0.9.1.dist-info/entry_points.txt
spectronote-0.9.1.dist-info/RECORD
