Metadata-Version: 2.4
Name: spectronote
Version: 0.9.1
Summary: 🎧 Piano-perfect audio spectrogram. Unlock a hidden absolute pitch in you.
Project-URL: GitHub, https://github.com/BrokenSource/SpectroNote
Project-URL: Changelog, https://brokensrc.dev/about/changelog
Project-URL: Funding, https://brokensrc.dev/about/sponsors
Project-URL: Contact, https://brokensrc.dev/about/contact
Project-URL: Download, https://brokensrc.dev/get/releases
Project-URL: Docs, https://brokensrc.dev/spectronote
Project-URL: Homepage, https://brokensrc.dev
Author-email: Tremeschin <29046864+Tremeschin@users.noreply.github.com>
License-Expression: AGPL-3.0
Requires-Python: >=3.10
Requires-Dist: broken-source==0.9.1
Requires-Dist: shaderflow==0.9.1
